setup.cfg
setup.py
hw_python_show_graph_lib/Easy.py
hw_python_show_graph_lib/Medium.py
hw_python_show_graph_lib/__init__.py
hw_python_show_graph_lib.egg-info/PKG-INFO
hw_python_show_graph_lib.egg-info/SOURCES.txt
hw_python_show_graph_lib.egg-info/dependency_links.txt
hw_python_show_graph_lib.egg-info/top_level.txt