Metadata-Version: 2.1
Name: hw-python-show-graph-lib
Version: 2.0
Summary: Python module for showing graph
Home-page: https://github.com/Deuqz/hw_python_show_graph_lib
Author: Deuqz
Author-email: ddemon2002@mail.ru
License: UNKNOWN
Platform: UNKNOWN
